jupyter_ext/__init__.py
jupyter_ext/_version.py
jupyter_ext/config.py
jupyter_ext/handlers.py
jupyter_ext/resource_usage.py
jupyter_ext/etc/jupyter/jupyter_server_config.d/hdsp_jupyter_extension.json
jupyter_ext/labextension/build_log.json
jupyter_ext/labextension/package.json
jupyter_ext/labextension/static/frontend_styles_index_js.4770ec0fb2d173b6deb4.js
jupyter_ext/labextension/static/frontend_styles_index_js.4770ec0fb2d173b6deb4.js.map
jupyter_ext/labextension/static/lib_index_js.29cf4312af19e86f82af.js
jupyter_ext/labextension/static/lib_index_js.29cf4312af19e86f82af.js.map
jupyter_ext/labextension/static/node_modules_emotion_use-insertion-effect-with-fallbacks_dist_emotion-use-insertion-effect-wi-3ba6b80.c095373419d05e6f141a.js
jupyter_ext/labextension/static/node_modules_emotion_use-insertion-effect-with-fallbacks_dist_emotion-use-insertion-effect-wi-3ba6b80.c095373419d05e6f141a.js.map
jupyter_ext/labextension/static/node_modules_emotion_use-insertion-effect-with-fallbacks_dist_emotion-use-insertion-effect-wi-3ba6b81.61e75fb98ecff46cf836.js
jupyter_ext/labextension/static/node_modules_emotion_use-insertion-effect-with-fallbacks_dist_emotion-use-insertion-effect-wi-3ba6b81.61e75fb98ecff46cf836.js.map
jupyter_ext/labextension/static/remoteEntry.61343eb4cf0577e74b50.js
jupyter_ext/labextension/static/remoteEntry.61343eb4cf0577e74b50.js.map
jupyter_ext/labextension/static/style.js
jupyter_ext/labextension/static/vendors-node_modules_babel_runtime_helpers_esm_extends_js-node_modules_emotion_serialize_dist-051195.e2553aab0c3963b83dd7.js
jupyter_ext/labextension/static/vendors-node_modules_babel_runtime_helpers_esm_extends_js-node_modules_emotion_serialize_dist-051195.e2553aab0c3963b83dd7.js.map
jupyter_ext/labextension/static/vendors-node_modules_emotion_cache_dist_emotion-cache_browser_development_esm_js-node_modules-782ee5.d9ed8645ef1d311657d8.js
hdsp_jupyter_extension-2.0.7.dist-info/METADATA
hdsp_jupyter_extension-2.0.7.dist-info/WHEEL
hdsp_jupyter_extension-2.0.7.dist-info/licenses/LICENSE
hdsp_jupyter_extension-2.0.7.dist-info/RECORD
