Metadata-Version: 2.4
Name: hdsp-jupyter-extension
Version: 2.0.7
Summary: HDSP Agent JupyterLab Extension - Thin client for Agent Server
Project-URL: Homepage, https://github.com/yourusername/hdsp-agent
Project-URL: Bug Tracker, https://github.com/yourusername/hdsp-agent/issues
Project-URL: Repository, https://github.com/yourusername/hdsp-agent.git
Author-email: Your Name <your.email@example.com>
License-File: LICENSE
Classifier: Framework :: Jupyter
Classifier: Framework :: Jupyter :: JupyterLab
Classifier: Framework :: Jupyter :: JupyterLab :: 4
Classifier: Framework :: Jupyter :: JupyterLab :: Extensions
Classifier: Framework :: Jupyter :: JupyterLab :: Extensions :: Prebuilt
Classifier: License :: OSI Approved :: MIT License
Classifier: Programming Language :: Python
Classifier: Programming Language :: Python :: 3
Classifier: Programming Language :: Python :: 3.10
Classifier: Programming Language :: Python :: 3.11
Classifier: Programming Language :: Python :: 3.12
Requires-Python: >=3.10
Requires-Dist: aiohttp>=3.11.0
Requires-Dist: certifi>=2024.0.0
Requires-Dist: fastapi>=0.115.0
Requires-Dist: httpx>=0.28.0
Requires-Dist: jupyter-server<3,>=2.0.1
Requires-Dist: langchain-core>=1.0.0
Requires-Dist: langchain-google-genai>=2.0.8
Requires-Dist: langchain-openai>=0.3.0
Requires-Dist: langchain>=1.0.0
Requires-Dist: langgraph>=1.0.0
Requires-Dist: psutil>=5.9.8
Requires-Dist: pydantic-settings>=2.6.0
Requires-Dist: pydantic>=2.10.0
Requires-Dist: sse-starlette>=2.2.0
Requires-Dist: tabulate>=0.9.0
Requires-Dist: uvicorn>=0.32.0
Provides-Extra: embedded
Requires-Dist: qdrant-client>=1.12.0; extra == 'embedded'
Requires-Dist: rank-bm25>=0.2.2; extra == 'embedded'
Requires-Dist: sentence-transformers<3.0.0,>=2.7.0; extra == 'embedded'
Requires-Dist: torch>=2.4.0; extra == 'embedded'
Requires-Dist: watchdog>=6.0.0; extra == 'embedded'
Provides-Extra: test
Requires-Dist: coverage; extra == 'test'
Requires-Dist: pytest; extra == 'test'
Requires-Dist: pytest-asyncio; extra == 'test'
Requires-Dist: pytest-cov; extra == 'test'
Requires-Dist: pytest-jupyter[server]>=0.6.0; extra == 'test'
